{"cameraMode":{"drawMode":0,"name":"Shaded","section":"Shading Mode"},"sceneLighting":true,"audioPlay":false,"sceneViewState":{"showFog":true,"showMaterialUpdate":false,"showSkybox":true,"showFlares":true,"showImageEffects":true,"showParticleSystems":true,"showVisualEffectGraphs":true,"m_FxEnabled":true},"in2DMode":false,"pivot":{"x":62.9189453125,"y":246.01107788085938,"z":274.780517578125},"rotation":{"x":-0.030916940420866014,"y":-0.9090077877044678,"z":0.4101802408695221,"w":-0.06819632649421692},"size":5.204625606536865,"orthographic":false}